zenodo_downloader/__init__.py
zenodo_downloader/cli.py
zenodo_downloader/downloader.py
zenodo_downloader-0.1.0.dist-info/LICENSE
zenodo_downloader-0.1.0.dist-info/METADATA
zenodo_downloader-0.1.0.dist-info/WHEEL
zenodo_downloader-0.1.0.dist-info/entry_points.txt
zenodo_downloader-0.1.0.dist-info/top_level.txt
zenodo_downloader-0.1.0.dist-info/RECORD
